{
  "documents": [
    {
      "id": "xqirby",
      "fields": {
        "username": {
          "stringValue": "xqirby"
        },
        "roles": {
          "arrayValue": {
            "values": [
              {
                "stringValue": "admin"
              }
            ]
          }
        },
        "display_name": {
          "stringValue": "xQirby"
        }
      }
    },
    {
      "id": "realrewins",
      "fields": {
        "username": {
          "stringValue": "realrewins"
        },
        "display_name": {
          "stringValue": "realRewins"
        },
        "roles": {
          "arrayValue": {
            "values": [
              {
                "stringValue": "viewer"
              }
            ]
          }
        }
      }
    },
    {
      "id": "xfibiiwife",
      "fields": {
        "username": {
          "stringValue": "xfibiiwife"
        },
        "display_name": {
          "stringValue": "xfibiiWife"
        },
        "roles": {
          "arrayValue": {
            "values": [
              {
                "stringValue": "viewer"
              }
            ]
          }
        }
      }
    }
  ]
}