{
  "316470254950": {
    "timestamp": "2026-02-22 12:27:09",
    "average": 868
  },
  "316460072678": {
    "timestamp": "2026-02-21 16:58:14",
    "average": 1093
  },
  "316459104486": {
    "timestamp": "2026-02-21 15:43:39",
    "average": 890
  },
  "316217575911": {
    "timestamp": "2026-02-20 17:19:56",
    "average": 875
  },
  "316203565671": {
    "timestamp": "2026-02-19 13:11:38",
    "average": 793
  },
  "316183608935": {
    "timestamp": "2026-02-17 15:50:40",
    "average": 807
  }
}